hqf_poetrydemo/__init__.py
hqf_poetrydemo/array_util.py
hqf_poetrydemo-0.1.0.dist-info/METADATA
hqf_poetrydemo-0.1.0.dist-info/WHEEL
hqf_poetrydemo-0.1.0.dist-info/RECORD
