Metadata-Version: 2.1
Name: hqf_poetrydemo
Version: 0.1.0
Summary: 
Author: hanqunfeng
Author-email: hanqf2008@163.com
Requires-Python: >=3.11,<4.0
Classifier: Programming Language :: Python :: 3
Classifier: Programming Language :: Python :: 3.11
Classifier: Programming Language :: Python :: 3.12
Classifier: Programming Language :: Python :: 3.13
Requires-Dist: numpy (>=2.1.3,<3.0.0)
